data_hasher_package/__init__.py
data_hasher_package/data_hashing.py
data_hasher_package-0.1.2.dist-info/METADATA
data_hasher_package-0.1.2.dist-info/WHEEL
data_hasher_package-0.1.2.dist-info/top_level.txt
data_hasher_package-0.1.2.dist-info/RECORD
