Metadata-Version: 2.1
Name: data_hasher_package
Version: 0.1.2
Summary: A package to hash data files and verify their hash using MD5.
Home-page: https://github.com/yourusername/mypackage
Author: Your Name
Author-email: your.email@example.com
Project-URL: Documentation, https://mypackages/docs
Project-URL: Source, https://github.com/yourusername/mypackage
Classifier: Programming Language :: Python :: 3
Classifier: Operating System :: OS Independent
Requires-Python: >=3.8
Requires-Dist: pandas==2.2.3
Provides-Extra: excel
Requires-Dist: openpyxl; extra == "excel"
